nevolution_snake/__init__.py
nevolution_snake/constants/__init__.py
nevolution_snake/constants/constants.py
nevolution_snake/env/__init__.py
nevolution_snake/env/snake_env.py
nevolution_snake/logic/__init__.py
nevolution_snake/logic/gamelogic.py
nevolution_snake/res/turkey.png
nevolution_snake/view/__init__.py
nevolution_snake/view/human.py
nevolution_snake/view/snake_gui.py
nevolution_snake-18.dist-info/METADATA
nevolution_snake-18.dist-info/WHEEL
nevolution_snake-18.dist-info/top_level.txt
nevolution_snake-18.dist-info/RECORD
